MGSurvE/Demo_STP.py
MGSurvE/__init__.py
MGSurvE/_version.py
MGSurvE/auxiliary.py
MGSurvE/colors.py
MGSurvE/constants.py
MGSurvE/kernels.py
MGSurvE/landscape.py
MGSurvE/matrices.py
MGSurvE/network.py
MGSurvE/optimization.py
MGSurvE/optimizationPSO.py
MGSurvE/plots.py
MGSurvE/pointProcess.py
MGSurvE-1.2.4.dist-info/LICENSE
MGSurvE-1.2.4.dist-info/METADATA
MGSurvE-1.2.4.dist-info/WHEEL
MGSurvE-1.2.4.dist-info/top_level.txt
MGSurvE-1.2.4.dist-info/RECORD
