Metadata-Version: 2.1
Name: MGSurvE
Version: 1.2.4
Summary: MGSurvE
Home-page: https://github.com/Chipdelmal/MGSurvE
Author: Hector M. Sanchez C.
Author-email: sanchez.hmsc@berkeley.edu
License: GPLv3
Classifier: Programming Language :: Python :: 3.9
Classifier: Programming Language :: Python :: 3.10
Classifier: Operating System :: OS Independent
License-File: LICENSE
Requires-Dist: deap
Requires-Dist: numpy
Requires-Dist: scikit-learn
Requires-Dist: scipy
Requires-Dist: matplotlib
Requires-Dist: sympy
Requires-Dist: ipython
Requires-Dist: jupyter
Requires-Dist: pandas
Requires-Dist: compress-pickle
Requires-Dist: dill
Requires-Dist: vincenty
Requires-Dist: haversine
Requires-Dist: networkx
Requires-Dist: pointpats
Requires-Dist: libpysal
Requires-Dist: geopandas
Requires-Dist: termcolor
Requires-Dist: tqdm
Provides-Extra: dev
Requires-Dist: pytest ; extra == 'dev'
Requires-Dist: ipykernel ; extra == 'dev'
Requires-Dist: jupyter ; extra == 'dev'
Requires-Dist: twine ; extra == 'dev'
Requires-Dist: wheel ; extra == 'dev'
Requires-Dist: sphinx ; extra == 'dev'
Requires-Dist: sphinx-rtd-theme ; extra == 'dev'
Requires-Dist: chardet ; extra == 'dev'
